pyticktick/__init__.py
pyticktick/client.py
pyticktick/logger.py
pyticktick/models/__init__.py
pyticktick/models/pydantic.py
pyticktick/models/v1/__init__.py
pyticktick/models/v1/parameters/__init__.py
pyticktick/models/v1/parameters/oauth.py
pyticktick/models/v1/parameters/project.py
pyticktick/models/v1/parameters/task.py
pyticktick/models/v1/responses/__init__.py
pyticktick/models/v1/responses/oauth.py
pyticktick/models/v1/responses/project.py
pyticktick/models/v1/responses/task.py
pyticktick/models/v2/__init__.py
pyticktick/models/v2/models.py
pyticktick/models/v2/parameters/__init__.py
pyticktick/models/v2/parameters/closed.py
pyticktick/models/v2/parameters/project.py
pyticktick/models/v2/parameters/project_group.py
pyticktick/models/v2/parameters/tag.py
pyticktick/models/v2/parameters/task.py
pyticktick/models/v2/parameters/task_parent.py
pyticktick/models/v2/responses/__init__.py
pyticktick/models/v2/responses/batch.py
pyticktick/models/v2/responses/closed.py
pyticktick/models/v2/responses/tag.py
pyticktick/models/v2/responses/task_parent.py
pyticktick/models/v2/responses/user.py
pyticktick/models/v2/types.py
pyticktick/pydantic.py
pyticktick/retry.py
pyticktick/settings.py
pyticktick-0.3.0.dist-info/WHEEL
pyticktick-0.3.0.dist-info/METADATA
pyticktick-0.3.0.dist-info/RECORD
