Metadata-Version: 2.3
Name: pyticktick
Version: 0.3.0
Summary: The modern library to interact with the TickTick API.
Author: Seb Pretzer
Author-email: Seb Pretzer <quick.creek3304@fastmail.com>
License: MIT License
Classifier: Programming Language :: Python :: 3
Classifier: License :: OSI Approved :: MIT License
Classifier: Operating System :: OS Independent
Requires-Dist: click>=5.0.0
Requires-Dist: httpx>=0.25.0
Requires-Dist: icalendar>=6.1.2
Requires-Dist: loguru>=0.7.0
Requires-Dist: pydantic-extra-types>=2.2.0
Requires-Dist: pydantic-settings>=2.0.0
Requires-Dist: pydantic[email]>=2.0.0
Requires-Dist: pymongo>=4.0.0
Requires-Dist: pyotp>=2.9.0
Requires-Dist: tenacity>=9.0.0
Requires-Python: >=3.10, <3.15
Project-URL: Changelog, https://pyticktick.pretzer.io/CHANGELOG
Project-URL: Homepage, https://pyticktick.pretzer.io/
Project-URL: Issues, https://github.com/sebpretzer/pyticktick/issues
Project-URL: Repository, https://github.com/sebpretzer/pyticktick
